trackdeps-1.0.2.dist-info/WHEEL
trackdeps-1.0.2.dist-info/entry_points.txt
trackdeps-1.0.2.dist-info/metadata.json
trackdeps-1.0.2.dist-info/METADATA
trackdeps-1.0.2.dist-info/RECORD
trackdeps-1.0.2.dist-info/DESCRIPTION.rst
trackdeps-1.0.2.dist-info/top_level.txt
trackdeps/tracker.py
trackdeps/__init__.py
trackdeps/report.py
trackdeps/parser.py
trackdeps/__main__.py
trackdeps/html/green.ico
trackdeps/html/style.css
trackdeps/html/template.html
trackdeps/html/orange.ico
