Metadata-Version: 2.0
Name: trackdeps
Version: 1.0.2
Summary: UNKNOWN
Home-page: http://trackdeps.pietroalbini.io
Author: Pietro Albini
Author-email: pietro@pietroalbini.io
License: MIT
Platform: UNKNOWN
Classifier: Environment :: Console
Classifier: Intended Audience :: Developers
Classifier: Intended Audience :: System Administrators
Classifier: License :: OSI Approved :: MIT License
Classifier: Natural Language :: English
Classifier: Programming Language :: Python :: 3
Classifier: Programming Language :: Python :: 3.3
Classifier: Programming Language :: Python :: 3.4
Classifier: Programming Language :: Python :: 3.5
Classifier: Programming Language :: Python :: 3 :: Only
Classifier: Topic :: Software Development :: Libraries
Classifier: Topic :: System :: Systems Administration
Classifier: Topic :: System :: Software Distribution
Requires-Dist: packaging
Requires-Dist: requests
Requires-Dist: setuptools
Requires-Dist: jinja2
Requires-Dist: pyyaml
Requires-Dist: click
Requires-Dist: csscompressor
Requires-Dist: django-htmlmin
